aimltools
