Metadata-Version: 2.1
Name: dia-aiml
Version: 1.0.5
Summary: A Python toolkit for the analysis of machine data
Home-page: https://github.com/EliLillyCo/MQIT_DIA_AIML_Toolkit
Author: Francesco Gabbanini, Manjunath Bagewadi, Henson Tauro
Author-email: fgabbanini@yahoo.it
License: MIT
Platform: UNKNOWN
License-File: LICENSE.txt
